[
{"id":14,"name":"Watch5","price":2000.0,"description":"undefined","quantity":6},
{"id":15,"name":"watch1","price":200.0,"description":"Good Watch","quantity":2},
{"id":17,"name":"Apple","price":400.0,"description":"Good Good","quantity":3},
{"id":18,"name":"test2","price":20000.0,"description":"test2test2test2","quantity":2},
{"id":14,"name":"Watch5","price":2000.0,"description":"undefined","quantity":6},
{"id":15,"name":"watch1","price":200.0,"description":"Good Watch","quantity":2},
{"id":17,"name":"Apple","price":400.0,"description":"Good Good","quantity":3},
{"id":18,"name":"test2","price":20000.0,"description":"test2test2test2","quantity":2},
{"id":14,"name":"Watch5","price":2000.0,"description":"undefined","quantity":6},
{"id":15,"name":"watch1","price":200.0,"description":"Good Watch","quantity":2},
{"id":17,"name":"Apple","price":400.0,"description":"Good Good","quantity":3},
{"id":18,"name":"test2","price":20000.0,"description":"test2test2test2","quantity":2},
{"id":14,"name":"Watch5","price":2000.0,"description":"undefined","quantity":6},
{"id":15,"name":"watch1","price":200.0,"description":"Good Watch","quantity":2},
{"id":17,"name":"Apple","price":400.0,"description":"Good Good","quantity":3},
{"id":18,"name":"test2","price":20000.0,"description":"test2test2test2","quantity":2},
{"id":14,"name":"Watch5","price":2000.0,"description":"undefined","quantity":6},
{"id":15,"name":"watch1","price":200.0,"description":"Good Watch","quantity":2},
{"id":17,"name":"Apple","price":400.0,"description":"Good Good","quantity":3},
{"id":18,"name":"test2","price":20000.0,"description":"test2test2test2","quantity":2},
{"id":19,"name":"wat3","price":456.0,"description":"kajsdflkasjfl","quantity":2}
]